sandboxes/__init__.py
sandboxes/agents/base.py
sandboxes/agents/factory.py
sandboxes/agents/installed/base.py
sandboxes/agents/installed/claude_code.py
sandboxes/agents/installed/install-claude-code.sh
sandboxes/agents/nop.py
sandboxes/agents/oracle.py
sandboxes/cli/sb/admin.py
sandboxes/cli/sb/cache.py
sandboxes/cli/sb/datasets.py
sandboxes/cli/sb/db.py
sandboxes/cli/sb/jobs.py
sandboxes/cli/sb/main.py
sandboxes/cli/sb/tasks.py
sandboxes/cli/sb/trials.py
sandboxes/environments/base.py
sandboxes/environments/docker/docker-compose.yaml
sandboxes/environments/docker/docker.py
sandboxes/environments/factory.py
sandboxes/job.py
sandboxes/mappers/terminal_bench.py
sandboxes/models/agent/name.py
sandboxes/models/agent/result.py
sandboxes/models/dataset_item.py
sandboxes/models/db/__init__.py
sandboxes/models/db/models.py
sandboxes/models/difficulty.py
sandboxes/models/environment_type.py
sandboxes/models/job/config.py
sandboxes/models/job/result.py
sandboxes/models/metric.py
sandboxes/models/orchestrator_type.py
sandboxes/models/registry.py
sandboxes/models/task/config.py
sandboxes/models/task/id.py
sandboxes/models/task/paths.py
sandboxes/models/task/task.py
sandboxes/models/trial/config.py
sandboxes/models/trial/paths.py
sandboxes/models/trial/result.py
sandboxes/models/verifier/result.py
sandboxes/orchestrators/base.py
sandboxes/orchestrators/factory.py
sandboxes/orchestrators/local.py
sandboxes/registry/client.py
sandboxes/tasks/client.py
sandboxes/trial/trial.py
sandboxes/verifier/verifier.py
sandboxes-0.1.0.dist-info/WHEEL
sandboxes-0.1.0.dist-info/entry_points.txt
sandboxes-0.1.0.dist-info/METADATA
sandboxes-0.1.0.dist-info/RECORD
